odoo/addons/mis_builder_budget/README.rst
odoo/addons/mis_builder_budget/__init__.py
odoo/addons/mis_builder_budget/__manifest__.py
odoo/addons/mis_builder_budget/i18n/ca.po
odoo/addons/mis_builder_budget/i18n/de.po
odoo/addons/mis_builder_budget/i18n/es.po
odoo/addons/mis_builder_budget/i18n/fr.po
odoo/addons/mis_builder_budget/i18n/hr.po
odoo/addons/mis_builder_budget/i18n/hr_HR.po
odoo/addons/mis_builder_budget/i18n/it.po
odoo/addons/mis_builder_budget/i18n/mis_builder_budget.pot
odoo/addons/mis_builder_budget/i18n/nl.po
odoo/addons/mis_builder_budget/i18n/nl_NL.po
odoo/addons/mis_builder_budget/i18n/pt.po
odoo/addons/mis_builder_budget/i18n/pt_BR.po
odoo/addons/mis_builder_budget/i18n/sv.po
odoo/addons/mis_builder_budget/models/__init__.py
odoo/addons/mis_builder_budget/models/mis_budget.py
odoo/addons/mis_builder_budget/models/mis_budget_abstract.py
odoo/addons/mis_builder_budget/models/mis_budget_by_account.py
odoo/addons/mis_builder_budget/models/mis_budget_by_account_item.py
odoo/addons/mis_builder_budget/models/mis_budget_item.py
odoo/addons/mis_builder_budget/models/mis_budget_item_abstract.py
odoo/addons/mis_builder_budget/models/mis_report_instance.py
odoo/addons/mis_builder_budget/models/mis_report_instance_period.py
odoo/addons/mis_builder_budget/models/mis_report_kpi.py
odoo/addons/mis_builder_budget/models/mis_report_kpi_expression.py
odoo/addons/mis_builder_budget/readme/CONTRIBUTORS.md
odoo/addons/mis_builder_budget/readme/DESCRIPTION.md
odoo/addons/mis_builder_budget/readme/HISTORY.md
odoo/addons/mis_builder_budget/readme/ROADMAP.md
odoo/addons/mis_builder_budget/readme/USAGE.md
odoo/addons/mis_builder_budget/readme/newsfragments/.gitignore
odoo/addons/mis_builder_budget/security/mis_budget.xml
odoo/addons/mis_builder_budget/security/mis_budget_by_account.xml
odoo/addons/mis_builder_budget/security/mis_budget_by_account_item.xml
odoo/addons/mis_builder_budget/security/mis_budget_item.xml
odoo/addons/mis_builder_budget/static/description/icon.png
odoo_addon_mis_builder_budget-18.0.2.0.0.4.dist-info/METADATA
odoo_addon_mis_builder_budget-18.0.2.0.0.4.dist-info/WHEEL
odoo_addon_mis_builder_budget-18.0.2.0.0.4.dist-info/top_level.txt
odoo_addon_mis_builder_budget-18.0.2.0.0.4.dist-info/RECORD
