Metadata-Version: 2.1
Name: odoo-addon-mis_builder_budget
Version: 18.0.2.0.0.4
Requires-Python: >=3.10
Requires-Dist: odoo-addon-mis_builder==18.0.*
Requires-Dist: odoo==18.0.*
Summary: Create budgets for MIS reports
Home-page: https://github.com/OCA/mis-builder
License: AGPL-3
Author: ACSONE SA/NV, Odoo Community Association (OCA)
Author-email: support@odoo-community.org
Classifier: Programming Language :: Python
Classifier: Framework :: Odoo
Classifier: Framework :: Odoo :: 18.0
Classifier: License :: OSI Approved :: GNU Affero General Public License v3
Classifier: Development Status :: 5 - Production/Stable
